[
    {
        "rel_err": 0.740080408112349, 
        "DtkNodeId": 830223056, 
        "abs_err": 2.847343683242798, 
        "Pf-Incidence-per-1000": 3.847343683242798, 
        "Longitude": -74.42916666666667, 
        "x_Local_Migration": 0.1, 
        "NodeLabel": 762, 
        "Latitude": 18.39583333333333, 
        "5yr-avg-Pf-Incidence-per-1000-model": 1.0, 
        "Population": 634.9598789219999
    }, 
    {
        "rel_err": 8.869437897313736, 
        "DtkNodeId": 831009506, 
        "abs_err": 29.207005977630615, 
        "Pf-Incidence-per-1000": 3.2929940223693848, 
        "Longitude": -74.32916666666667, 
        "x_Local_Migration": 0.1, 
        "NodeLabel": 749, 
        "Latitude": 18.545833333333334, 
        "5yr-avg-Pf-Incidence-per-1000-model": 32.5, 
        "Population": 1963.33138776
    }, 
    {
        "rel_err": 0.6031931084349978, 
        "DtkNodeId": 830681799, 
        "abs_err": 1.5201175212860107, 
        "Pf-Incidence-per-1000": 2.5201175212860107, 
        "Longitude": -74.37083333333334, 
        "x_Local_Migration": 0.1, 
        "NodeLabel": 612, 
        "Latitude": 18.320833333333326, 
        "5yr-avg-Pf-Incidence-per-1000-model": 1.0, 
        "Population": 6267.976711270001
    }, 
    {
        "rel_err": 1.0, 
        "DtkNodeId": 830943974, 
        "abs_err": 2.8666815757751465, 
        "Pf-Incidence-per-1000": 2.8666815757751465, 
        "Longitude": -74.3375, 
        "x_Local_Migration": 0.1, 
        "NodeLabel": 927, 
        "Latitude": 18.579166666666666, 
        "5yr-avg-Pf-Incidence-per-1000-model": 0.0, 
        "Population": 233.54397821400002
    }, 
    {
        "rel_err": 0.6861353649294937, 
        "DtkNodeId": 833368797, 
        "abs_err": 2.186086893081665, 
        "Pf-Incidence-per-1000": 3.186086893081665, 
        "Longitude": -74.02916666666667, 
        "x_Local_Migration": 0.1, 
        "NodeLabel": 280, 
        "Latitude": 18.504166666666663, 
        "5yr-avg-Pf-Incidence-per-1000-model": 1.0, 
        "Population": 531.151830196
    }, 
    {
        "rel_err": 0.44210985835086647, 
        "DtkNodeId": 832647901, 
        "abs_err": 0.7924675941467285, 
        "Pf-Incidence-per-1000": 1.7924675941467285, 
        "Longitude": -74.12083333333334, 
        "x_Local_Migration": 0.1, 
        "NodeLabel": 550, 
        "Latitude": 18.504166666666663, 
        "5yr-avg-Pf-Incidence-per-1000-model": 1.0, 
        "Population": 209.53980732
    }, 
    {
        "rel_err": 1.0, 
        "DtkNodeId": 830419672, 
        "abs_err": 2.4063377380371094, 
        "Pf-Incidence-per-1000": 2.4063377380371094, 
        "Longitude": -74.40416666666667, 
        "x_Local_Migration": 0.1, 
        "NodeLabel": 202, 
        "Latitude": 18.46249999999999, 
        "5yr-avg-Pf-Incidence-per-1000-model": 0.0, 
        "Population": 422.493350983
    }, 
    {
        "rel_err": 8.708860597682616, 
        "DtkNodeId": 831140588, 
        "abs_err": 30.049543619155884, 
        "Pf-Incidence-per-1000": 3.450456380844116, 
        "Longitude": -74.3125, 
        "x_Local_Migration": 0.1, 
        "NodeLabel": 543, 
        "Latitude": 18.629166666666663, 
        "5yr-avg-Pf-Incidence-per-1000-model": 33.5, 
        "Population": 15990.425630300002
    }, 
    {
        "rel_err": 0.17045466232396678, 
        "DtkNodeId": 832910057, 
        "abs_err": 0.8219184875488281, 
        "Pf-Incidence-per-1000": 4.821918487548828, 
        "Longitude": -74.0875, 
        "x_Local_Migration": 0.1, 
        "NodeLabel": 1299, 
        "Latitude": 18.60416666666667, 
        "5yr-avg-Pf-Incidence-per-1000-model": 4.0, 
        "Population": 324.173687935
    }, 
    {
        "rel_err": 1.0, 
        "DtkNodeId": 831009481, 
        "abs_err": 2.3832576274871826, 
        "Pf-Incidence-per-1000": 2.3832576274871826, 
        "Longitude": -74.32916666666667, 
        "x_Local_Migration": 0.1, 
        "NodeLabel": 274, 
        "Latitude": 18.33749999999999, 
        "5yr-avg-Pf-Incidence-per-1000-model": 0.0, 
        "Population": 466.239425659
    }, 
    {
        "rel_err": 1.0, 
        "DtkNodeId": 832385762, 
        "abs_err": 1.4115004539489746, 
        "Pf-Incidence-per-1000": 1.4115004539489746, 
        "Longitude": -74.15416666666667, 
        "x_Local_Migration": 0.1, 
        "NodeLabel": 358, 
        "Latitude": 18.545833333333334, 
        "5yr-avg-Pf-Incidence-per-1000-model": 0.0, 
        "Population": 5705.306934360001
    }, 
    {
        "rel_err": 10.195656528553432, 
        "DtkNodeId": 830354147, 
        "abs_err": 61.015536308288574, 
        "Pf-Incidence-per-1000": 5.984463691711426, 
        "Longitude": -74.41250000000001, 
        "x_Local_Migration": 0.1, 
        "NodeLabel": 912, 
        "Latitude": 18.55416666666666, 
        "5yr-avg-Pf-Incidence-per-1000-model": 67.0, 
        "Population": 14720.8542218
    }, 
    {
        "rel_err": 1.0, 
        "DtkNodeId": 830354127, 
        "abs_err": 3.7401928901672363, 
        "Pf-Incidence-per-1000": 3.7401928901672363, 
        "Longitude": -74.41250000000001, 
        "x_Local_Migration": 0.1, 
        "NodeLabel": 64, 
        "Latitude": 18.387500000000003, 
        "5yr-avg-Pf-Incidence-per-1000-model": 0.0, 
        "Population": 169.95258426700002
    }, 
    {
        "rel_err": 0.7905548585653658, 
        "DtkNodeId": 831533806, 
        "abs_err": 1.8872599601745605, 
        "Pf-Incidence-per-1000": 2.3872599601745605, 
        "Longitude": -74.2625, 
        "x_Local_Migration": 0.1, 
        "NodeLabel": 626, 
        "Latitude": 18.64583333333333, 
        "5yr-avg-Pf-Incidence-per-1000-model": 0.5, 
        "Population": 1445.31600571
    }, 
    {
        "rel_err": 0.08063552808641207, 
        "DtkNodeId": 831533807, 
        "abs_err": 0.2192697525024414, 
        "Pf-Incidence-per-1000": 2.7192697525024414, 
        "Longitude": -74.2625, 
        "x_Local_Migration": 0.1, 
        "NodeLabel": 284, 
        "Latitude": 18.65416666666667, 
        "5yr-avg-Pf-Incidence-per-1000-model": 2.5, 
        "Population": 388.524991989
    }, 
    {
        "rel_err": 0.9088114219482347, 
        "DtkNodeId": 830091990, 
        "abs_err": 4.983142852783203, 
        "Pf-Incidence-per-1000": 5.483142852783203, 
        "Longitude": -74.44583333333334, 
        "x_Local_Migration": 0.1, 
        "NodeLabel": 736, 
        "Latitude": 18.445833333333326, 
        "5yr-avg-Pf-Incidence-per-1000-model": 0.5, 
        "Population": 872.3230056760001
    }, 
    {
        "rel_err": 0.40296631072334854, 
        "DtkNodeId": 831926982, 
        "abs_err": 1.687368392944336, 
        "Pf-Incidence-per-1000": 4.187368392944336, 
        "Longitude": -74.2125, 
        "x_Local_Migration": 0.1, 
        "NodeLabel": 1147, 
        "Latitude": 18.3125, 
        "5yr-avg-Pf-Incidence-per-1000-model": 2.5, 
        "Population": 13975.194802300002
    }, 
    {
        "rel_err": 1.0, 
        "DtkNodeId": 830812900, 
        "abs_err": 2.003969669342041, 
        "Pf-Incidence-per-1000": 2.003969669342041, 
        "Longitude": -74.35416666666667, 
        "x_Local_Migration": 0.1, 
        "NodeLabel": 1128, 
        "Latitude": 18.5625, 
        "5yr-avg-Pf-Incidence-per-1000-model": 0.0, 
        "Population": 290.968924522
    }, 
    {
        "rel_err": 0.7417780206718986, 
        "DtkNodeId": 833565406, 
        "abs_err": 2.8726370334625244, 
        "Pf-Incidence-per-1000": 3.8726370334625244, 
        "Longitude": -74.00416666666666, 
        "x_Local_Migration": 0.1, 
        "NodeLabel": 570, 
        "Latitude": 18.512500000000003, 
        "5yr-avg-Pf-Incidence-per-1000-model": 1.0, 
        "Population": 5402.54377317
    }, 
    {
        "rel_err": 0.33279596025374036, 
        "DtkNodeId": 830550758, 
        "abs_err": 1.498185634613037, 
        "Pf-Incidence-per-1000": 4.501814365386963, 
        "Longitude": -74.3875, 
        "x_Local_Migration": 0.1, 
        "NodeLabel": 269, 
        "Latitude": 18.579166666666666, 
        "5yr-avg-Pf-Incidence-per-1000-model": 6.0, 
        "Population": 769.2389879229999
    }, 
    {
        "rel_err": 0.11878121610513351, 
        "DtkNodeId": 832254686, 
        "abs_err": 0.13479197025299072, 
        "Pf-Incidence-per-1000": 1.1347919702529907, 
        "Longitude": -74.17083333333333, 
        "x_Local_Migration": 0.1, 
        "NodeLabel": 860, 
        "Latitude": 18.512500000000003, 
        "5yr-avg-Pf-Incidence-per-1000-model": 1.0, 
        "Population": 453.94572162599997
    }, 
    {
        "rel_err": 0.7176259082408615, 
        "DtkNodeId": 832713407, 
        "abs_err": 2.5414013862609863, 
        "Pf-Incidence-per-1000": 3.5414013862609863, 
        "Longitude": -74.1125, 
        "x_Local_Migration": 0.1, 
        "NodeLabel": 75, 
        "Latitude": 18.254166666666663, 
        "5yr-avg-Pf-Incidence-per-1000-model": 1.0, 
        "Population": 553.7378644940001
    }, 
    {
        "rel_err": 0.6462432644336457, 
        "DtkNodeId": 831075014, 
        "abs_err": 0.9134006500244141, 
        "Pf-Incidence-per-1000": 1.413400650024414, 
        "Longitude": -74.32083333333334, 
        "x_Local_Migration": 0.1, 
        "NodeLabel": 1059, 
        "Latitude": 18.3125, 
        "5yr-avg-Pf-Incidence-per-1000-model": 0.5, 
        "Population": 200.06379056
    }, 
    {
        "rel_err": 0.7205508121261497, 
        "DtkNodeId": 833041116, 
        "abs_err": 1.2892340421676636, 
        "Pf-Incidence-per-1000": 1.7892340421676636, 
        "Longitude": -74.07083333333334, 
        "x_Local_Migration": 0.1, 
        "NodeLabel": 85, 
        "Latitude": 18.495833333333337, 
        "5yr-avg-Pf-Incidence-per-1000-model": 0.5, 
        "Population": 116.05900144600001
    }, 
    {
        "rel_err": 0.8099030004505072, 
        "DtkNodeId": 833106657, 
        "abs_err": 2.1302361488342285, 
        "Pf-Incidence-per-1000": 2.6302361488342285, 
        "Longitude": -74.0625, 
        "x_Local_Migration": 0.1, 
        "NodeLabel": 976, 
        "Latitude": 18.537499999999994, 
        "5yr-avg-Pf-Incidence-per-1000-model": 0.5, 
        "Population": 5081.54337406
    }, 
    {
        "rel_err": 1.0, 
        "DtkNodeId": 830419665, 
        "abs_err": 3.5083255767822266, 
        "Pf-Incidence-per-1000": 3.5083255767822266, 
        "Longitude": -74.40416666666667, 
        "x_Local_Migration": 0.1, 
        "NodeLabel": 795, 
        "Latitude": 18.40416666666667, 
        "5yr-avg-Pf-Incidence-per-1000-model": 0.0, 
        "Population": 550.745526314
    }, 
    {
        "rel_err": 1.0, 
        "DtkNodeId": 832910015, 
        "abs_err": 1.8343408107757568, 
        "Pf-Incidence-per-1000": 1.8343408107757568, 
        "Longitude": -74.0875, 
        "x_Local_Migration": 0.1, 
        "NodeLabel": 132, 
        "Latitude": 18.254166666666663, 
        "5yr-avg-Pf-Incidence-per-1000-model": 0.0, 
        "Population": 8849.048700569998
    }, 
    {
        "rel_err": 0.6779027011053879, 
        "DtkNodeId": 833106651, 
        "abs_err": 1.052325963973999, 
        "Pf-Incidence-per-1000": 1.552325963973999, 
        "Longitude": -74.0625, 
        "x_Local_Migration": 0.1, 
        "NodeLabel": 531, 
        "Latitude": 18.487499999999997, 
        "5yr-avg-Pf-Incidence-per-1000-model": 0.5, 
        "Population": 946.6604566569999
    }, 
    {
        "rel_err": 0.716214576839551, 
        "DtkNodeId": 833106652, 
        "abs_err": 1.2618945837020874, 
        "Pf-Incidence-per-1000": 1.7618945837020874, 
        "Longitude": -74.0625, 
        "x_Local_Migration": 0.1, 
        "NodeLabel": 674, 
        "Latitude": 18.495833333333337, 
        "5yr-avg-Pf-Incidence-per-1000-model": 0.5, 
        "Population": 158.381608963
    }, 
    {
        "rel_err": 0.04848436246672041, 
        "DtkNodeId": 831927013, 
        "abs_err": 0.11560583114624023, 
        "Pf-Incidence-per-1000": 2.3843941688537598, 
        "Longitude": -74.2125, 
        "x_Local_Migration": 0.1, 
        "NodeLabel": 385, 
        "Latitude": 18.570833333333326, 
        "5yr-avg-Pf-Incidence-per-1000-model": 2.5, 
        "Population": 8126.877784969999
    }, 
    {
        "rel_err": 0.44871932261269, 
        "DtkNodeId": 832647872, 
        "abs_err": 1.2209370136260986, 
        "Pf-Incidence-per-1000": 2.7209370136260986, 
        "Longitude": -74.12083333333334, 
        "x_Local_Migration": 0.1, 
        "NodeLabel": 189, 
        "Latitude": 18.262500000000003, 
        "5yr-avg-Pf-Incidence-per-1000-model": 1.5, 
        "Population": 377.90406990099996
    }, 
    {
        "rel_err": 1.0, 
        "DtkNodeId": 830681826, 
        "abs_err": 2.6980490684509277, 
        "Pf-Incidence-per-1000": 2.6980490684509277, 
        "Longitude": -74.37083333333334, 
        "x_Local_Migration": 0.1, 
        "NodeLabel": 569, 
        "Latitude": 18.545833333333334, 
        "5yr-avg-Pf-Incidence-per-1000-model": 0.0, 
        "Population": 2841.46038055
    }, 
    {
        "rel_err": 0.8187887654412623, 
        "DtkNodeId": 832385731, 
        "abs_err": 2.2592108249664307, 
        "Pf-Incidence-per-1000": 2.7592108249664307, 
        "Longitude": -74.15416666666667, 
        "x_Local_Migration": 0.1, 
        "NodeLabel": 431, 
        "Latitude": 18.287499999999994, 
        "5yr-avg-Pf-Incidence-per-1000-model": 0.5, 
        "Population": 7864.084071399999
    }, 
    {
        "rel_err": 1.0, 
        "DtkNodeId": 830943971, 
        "abs_err": 2.2813596725463867, 
        "Pf-Incidence-per-1000": 2.2813596725463867, 
        "Longitude": -74.3375, 
        "x_Local_Migration": 0.1, 
        "NodeLabel": 157, 
        "Latitude": 18.55416666666666, 
        "5yr-avg-Pf-Incidence-per-1000-model": 0.0, 
        "Population": 417.101854324
    }, 
    {
        "rel_err": 0.8359127666889345, 
        "DtkNodeId": 830616287, 
        "abs_err": 2.5471596717834473, 
        "Pf-Incidence-per-1000": 3.0471596717834473, 
        "Longitude": -74.37916666666666, 
        "x_Local_Migration": 0.1, 
        "NodeLabel": 489, 
        "Latitude": 18.52083333333333, 
        "5yr-avg-Pf-Incidence-per-1000-model": 0.5, 
        "Population": 258.004165649
    }, 
    {
        "rel_err": 0.06708648243925311, 
        "DtkNodeId": 830157531, 
        "abs_err": 0.3772130012512207, 
        "Pf-Incidence-per-1000": 5.622786998748779, 
        "Longitude": -74.4375, 
        "x_Local_Migration": 0.1, 
        "NodeLabel": 780, 
        "Latitude": 18.487499999999997, 
        "5yr-avg-Pf-Incidence-per-1000-model": 6.0, 
        "Population": 17367.8886738
    }, 
    {
        "rel_err": 3.711315709409368, 
        "DtkNodeId": 830157536, 
        "abs_err": 30.328185081481934, 
        "Pf-Incidence-per-1000": 8.171814918518066, 
        "Longitude": -74.4375, 
        "x_Local_Migration": 0.1, 
        "NodeLabel": 251, 
        "Latitude": 18.52916666666667, 
        "5yr-avg-Pf-Incidence-per-1000-model": 38.5, 
        "Population": 751.4595508579998
    }, 
    {
        "rel_err": 0.4691370410606364, 
        "DtkNodeId": 831664880, 
        "abs_err": 1.3255879878997803, 
        "Pf-Incidence-per-1000": 2.8255879878997803, 
        "Longitude": -74.24583333333334, 
        "x_Local_Migration": 0.1, 
        "NodeLabel": 473, 
        "Latitude": 18.662499999999994, 
        "5yr-avg-Pf-Incidence-per-1000-model": 1.5, 
        "Population": 114.645618439
    }, 
    {
        "rel_err": 0.7382539848160872, 
        "DtkNodeId": 830354151, 
        "abs_err": 4.230746269226074, 
        "Pf-Incidence-per-1000": 5.730746269226074, 
        "Longitude": -74.41250000000001, 
        "x_Local_Migration": 0.1, 
        "NodeLabel": 1290, 
        "Latitude": 18.58749999999999, 
        "5yr-avg-Pf-Incidence-per-1000-model": 1.5, 
        "Population": 782.666756153
    }, 
    {
        "rel_err": 0.21040309821843403, 
        "DtkNodeId": 830091985, 
        "abs_err": 1.199110507965088, 
        "Pf-Incidence-per-1000": 5.699110507965088, 
        "Longitude": -74.44583333333334, 
        "x_Local_Migration": 0.1, 
        "NodeLabel": 1321, 
        "Latitude": 18.40416666666667, 
        "5yr-avg-Pf-Incidence-per-1000-model": 4.5, 
        "Population": 2066.67096019
    }, 
    {
        "rel_err": 1.0, 
        "DtkNodeId": 831206089, 
        "abs_err": 1.9695022106170654, 
        "Pf-Incidence-per-1000": 1.9695022106170654, 
        "Longitude": -74.30416666666667, 
        "x_Local_Migration": 0.1, 
        "NodeLabel": 675, 
        "Latitude": 18.33749999999999, 
        "5yr-avg-Pf-Incidence-per-1000-model": 0.0, 
        "Population": 462.272230864
    }, 
    {
        "rel_err": 1.0, 
        "DtkNodeId": 833630945, 
        "abs_err": 5.698655128479004, 
        "Pf-Incidence-per-1000": 5.698655128479004, 
        "Longitude": -73.99583333333334, 
        "x_Local_Migration": 0.1, 
        "NodeLabel": 1069, 
        "Latitude": 18.537499999999994, 
        "5yr-avg-Pf-Incidence-per-1000-model": 0.0, 
        "Population": 185.979195356
    }, 
    {
        "rel_err": 0.8747516266476254, 
        "DtkNodeId": 832516845, 
        "abs_err": 3.492067813873291, 
        "Pf-Incidence-per-1000": 3.992067813873291, 
        "Longitude": -74.1375, 
        "x_Local_Migration": 0.1, 
        "NodeLabel": 20, 
        "Latitude": 18.637500000000003, 
        "5yr-avg-Pf-Incidence-per-1000-model": 0.5, 
        "Population": 48539.6061859
    }, 
    {
        "rel_err": 0.9153939086254278, 
        "DtkNodeId": 830223070, 
        "abs_err": 5.409739971160889, 
        "Pf-Incidence-per-1000": 5.909739971160889, 
        "Longitude": -74.42916666666667, 
        "x_Local_Migration": 0.1, 
        "NodeLabel": 1011, 
        "Latitude": 18.512500000000003, 
        "5yr-avg-Pf-Incidence-per-1000-model": 0.5, 
        "Population": 681.69836545
    }, 
    {
        "rel_err": 0.8795559802984636, 
        "DtkNodeId": 832516840, 
        "abs_err": 3.65130615234375, 
        "Pf-Incidence-per-1000": 4.15130615234375, 
        "Longitude": -74.1375, 
        "x_Local_Migration": 0.1, 
        "NodeLabel": 800, 
        "Latitude": 18.59583333333333, 
        "5yr-avg-Pf-Incidence-per-1000-model": 0.5, 
        "Population": 1714.67030859
    }, 
    {
        "rel_err": 0.4049104660588318, 
        "DtkNodeId": 831402732, 
        "abs_err": 1.1528434753417969, 
        "Pf-Incidence-per-1000": 2.847156524658203, 
        "Longitude": -74.27916666666667, 
        "x_Local_Migration": 0.1, 
        "NodeLabel": 933, 
        "Latitude": 18.629166666666663, 
        "5yr-avg-Pf-Incidence-per-1000-model": 4.0, 
        "Population": 379.927083969
    }
]